cdev_cli/__init__.py
cdev_cli/__main__.py
cdev_cli/lib.py
cdev_cli-0.1.1.dist-info/LICENSE
cdev_cli-0.1.1.dist-info/METADATA
cdev_cli-0.1.1.dist-info/WHEEL
cdev_cli-0.1.1.dist-info/entry_points.txt
cdev_cli-0.1.1.dist-info/RECORD
