Metadata-Version: 2.1
Name: cdev-cli
Version: 0.1.1
Summary: CLI interface to run a C development environment through docker.
Home-page: https://github.com/matteospanio/cdev-cli
License: MIT
Keywords: cdev,cli,docker,unipd,teaching
Author: Matteo Spanio
Author-email: spanio@dei.unipd.it
Requires-Python: >=3.8,<4.0
Classifier: Development Status :: 3 - Alpha
Classifier: Environment :: Console
Classifier: Intended Audience :: Developers
Classifier: License :: OSI Approved :: MIT License
Classifier: Operating System :: OS Independent
Classifier: Programming Language :: Python :: 3
Classifier: Programming Language :: Python :: 3.8
Classifier: Programming Language :: Python :: 3.9
Classifier: Programming Language :: Python :: 3.10
Classifier: Programming Language :: Python :: 3.11
Classifier: Programming Language :: Python :: 3.12
Project-URL: Repository, https://github.com/matteospanio/cdev-cli
